bayesml/.DS_Store
bayesml/__init__.py
bayesml/_check.py
bayesml/_exceptions.py
bayesml/base.py
bayesml/autoregressive/__init__.py
bayesml/autoregressive/_autoregressive.py
bayesml/bernoulli/__init__.py
bayesml/bernoulli/_bernoulli.py
bayesml/categorical/__init__.py
bayesml/categorical/_categorical.py
bayesml/contexttree/__init__.py
bayesml/contexttree/_contexttree.py
bayesml/exponential/__init__.py
bayesml/exponential/_exponential.py
bayesml/gaussianmixture/__init__.py
bayesml/gaussianmixture/_gaussianmixture.py
bayesml/hiddenmarkovnormal/__init__.py
bayesml/hiddenmarkovnormal/_hiddenmarkovnormal.py
bayesml/linearregression/__init__.py
bayesml/linearregression/_linearregression.py
bayesml/linearregressionmixture/__init__.py
bayesml/linearregressionmixture/_linearregressionmixture.py
bayesml/logisticregression/__init__.py
bayesml/logisticregression/_logisticregression.py
bayesml/metatree/__init__.py
bayesml/metatree/_metatree.py
bayesml/multivariate_normal/__init__.py
bayesml/multivariate_normal/_multivariatenormal.py
bayesml/normal/__init__.py
bayesml/normal/_normal.py
bayesml/poisson/__init__.py
bayesml/poisson/_poisson.py
bayesml-0.4.1.dist-info/LICENSE.txt
bayesml-0.4.1.dist-info/METADATA
bayesml-0.4.1.dist-info/WHEEL
bayesml-0.4.1.dist-info/top_level.txt
bayesml-0.4.1.dist-info/RECORD
