Metadata-Version: 2.2
Name: bayesml
Version: 0.4.1
Summary: Your First Library for Bayesian Machine Learning
Home-page: https://bayesml.github.io/BayesML/
Author: Yuta Nakahara et al.
Author-email: y.nakahara@waseda.jp
Classifier: Development Status :: 3 - Alpha
Classifier: License :: OSI Approved :: BSD License
Classifier: Intended Audience :: Education
Classifier: Intended Audience :: Science/Research
Classifier: Programming Language :: Python :: 3
Classifier: Programming Language :: Python :: 3.7
Classifier: Programming Language :: Python :: 3.8
Classifier: Programming Language :: Python :: 3.9
Classifier: Programming Language :: Python :: 3.10
Classifier: Programming Language :: Python :: 3.11
Classifier: Topic :: Scientific/Engineering
Requires-Python: ~=3.7
License-File: LICENSE.txt
Requires-Dist: numpy>=1.20
Requires-Dist: scipy>=1.7
Requires-Dist: matplotlib>=3.5
Requires-Dist: scikit-learn>=1.1
Dynamic: author
Dynamic: author-email
Dynamic: classifier
Dynamic: description
Dynamic: description-content-type
Dynamic: home-page
Dynamic: requires-dist
Dynamic: requires-python
Dynamic: summary
